lsproxy/__init__.py
lsproxy/_base_client.py
lsproxy/_client.py
lsproxy/_compat.py
lsproxy/_constants.py
lsproxy/_exceptions.py
lsproxy/_files.py
lsproxy/_models.py
lsproxy/_qs.py
lsproxy/_resource.py
lsproxy/_response.py
lsproxy/_streaming.py
lsproxy/_types.py
lsproxy/_version.py
lsproxy/py.typed
lsproxy/_utils/__init__.py
lsproxy/_utils/_logs.py
lsproxy/_utils/_proxy.py
lsproxy/_utils/_reflection.py
lsproxy/_utils/_streams.py
lsproxy/_utils/_sync.py
lsproxy/_utils/_transform.py
lsproxy/_utils/_typing.py
lsproxy/_utils/_utils.py
lsproxy/lib/.keep
lsproxy/resources/__init__.py
lsproxy/resources/symbols.py
lsproxy/resources/workspace.py
lsproxy/types/__init__.py
lsproxy/types/definition_response.py
lsproxy/types/references_response.py
lsproxy/types/symbol_definitions_in_file_params.py
lsproxy/types/symbol_find_definition_params.py
lsproxy/types/symbol_find_references_params.py
lsproxy/types/symbol_response.py
lsproxy/types/workspace_list_files_response.py
lsproxy/types/workspace_search_symbols_params.py
lsproxy/types/shared/__init__.py
lsproxy/types/shared/file_position.py
lsproxy/types/shared/position.py
lsproxy/types/shared/symbol.py
lsproxy/types/shared/symbol_response.py
lsproxy/types/shared_params/__init__.py
lsproxy/types/shared_params/file_position.py
lsproxy/types/shared_params/position.py
lsproxy-0.1.0a5.dist-info/METADATA
lsproxy-0.1.0a5.dist-info/WHEEL
lsproxy-0.1.0a5.dist-info/licenses/LICENSE
lsproxy-0.1.0a5.dist-info/RECORD
